setup.py
mbtapy/__init__.py
mbtapy.egg-info/PKG-INFO
mbtapy.egg-info/SOURCES.txt
mbtapy.egg-info/dependency_links.txt
mbtapy.egg-info/requires.txt
mbtapy.egg-info/top_level.txt