Metadata-Version: 1.0
Name: mbtapy
Version: 0.1.0.dev1
Summary: Python bindings for the MBTA-REALTIME API (v2)
Home-page: https://github.com/JDougherty/mbtapy
Author: Joseph Dougherty
Author-email: mbtapy@jwdougherty.com
License: LICENSE
Platform: UNKNOWN
